jwt_drf_passwordless/__init__.py
jwt_drf_passwordless/apps.py
jwt_drf_passwordless/compat.py
jwt_drf_passwordless/conf.py
jwt_drf_passwordless/constants.py
jwt_drf_passwordless/email.py
jwt_drf_passwordless/migrations/0001_initial.py
jwt_drf_passwordless/migrations/0002_alter_passwordlesschallengetoken_id_and_more.py
jwt_drf_passwordless/migrations/__init__.py
jwt_drf_passwordless/models.py
jwt_drf_passwordless/serializers.py
jwt_drf_passwordless/services.py
jwt_drf_passwordless/settings.py
jwt_drf_passwordless/signals.py
jwt_drf_passwordless/sms.py
jwt_drf_passwordless/templates/email/passwordless_request.html
jwt_drf_passwordless/templates/mobile/passwordless_request.txt
jwt_drf_passwordless/urls.py
jwt_drf_passwordless/utils.py
jwt_drf_passwordless/views.py
jwt_drf_passwordless-0.1.5.dist-info/LICENSE
jwt_drf_passwordless-0.1.5.dist-info/METADATA
jwt_drf_passwordless-0.1.5.dist-info/WHEEL
jwt_drf_passwordless-0.1.5.dist-info/RECORD
