Metadata-Version: 2.3
Name: jwt-drf-passwordless
Version: 0.1.5
Summary: A passworldess plugin for Django Rest Framework authentication package
License: MIT
Author: Sergio
Author-email: smaisidoro@gmail.com
Requires-Python: >=3.10,<4.0
Classifier: License :: OSI Approved :: MIT License
Classifier: Programming Language :: Python :: 3
Classifier: Programming Language :: Python :: 3.10
Classifier: Programming Language :: Python :: 3.11
Classifier: Programming Language :: Python :: 3.12
Classifier: Programming Language :: Python :: 3.13
Requires-Dist: django (>=5.2.4,<6.0.0)
Requires-Dist: django-phonenumber-field[phonenumberslite] (>=8.1.0,<9.0.0)
Requires-Dist: django-sms (>=0.7.0,<0.8.0)
Requires-Dist: django-templated-mail-2 (>=1.1.2,<2.0.0)
Requires-Dist: djangorestframework (>=3.16.0,<4.0.0)
Requires-Dist: djangorestframework-simplejwt (>=5.5.0,<6.0.0)
